{
  "id": "ashlu-creek-play-run",
  "url": "https://www.bcwhitewater.org/reaches/ashlu-creek-play-run",
  "source": "bcwhitewater.org",
  "country": "Canada",
  "province": "British Columbia",
  "last_updated": "2025-11-18T19:08:07.140894Z",
  "title": "Ashlu Creek - Play Run",
  "river_name": "Ashlu Creek",
  "section_name": "Play Run",
  "contributor": "David Wortley",
  "whats_it_like": "Boulder Garden fun which is now sadly tricky to access!",
  "difficulty": {
    "text": "III+ (IV-)",
    "min": 3,
    "max": 4
  },
  "scouting_portaging": "Scout the take-out, be aware of wood especially in 2 steeper drops.",
  "time": {
    "original": "A big day out"
  },
  "when_to_go": "Summer/Fall"
}